termii/__init__.py
termii/termii.py
termii_python_client-1.3.1.dist-info/LICENSE
termii_python_client-1.3.1.dist-info/METADATA
termii_python_client-1.3.1.dist-info/WHEEL
termii_python_client-1.3.1.dist-info/top_level.txt
termii_python_client-1.3.1.dist-info/RECORD
